azure_file_share_service
